{
  "slug": "fox-cities",
  "title": "Fox Cities, WI",
  "state": "wisconsin",
  "parent": "wisconsin",
  "sections": [
    {
      "id": "section-0",
      "title": "",
      "initiatives": [
        {
          "name": "Hate Free Outagmie",
          "url": "https://www.instagram.com/hatefreeoutagamie/",
          "description": "Outagmie County antifascist organizing"
        },
        {
          "name": "Appleton Screening",
          "url": "https://www.instagram.com/appletonscreening/",
          "description": "reading and movie club spreading awareness in Appleton, WI & beyond"
        },
        {
          "name": "Food Not Bombs Fox Valley",
          "url": "https://www.instagram.com/foodnotbombs_foxvalley/",
          "description": "Mutual aid org. based in the Fox Cities of Wisconsin. DM for more information or to get involved!"
        },
        {
          "name": "Hope Fridge",
          "url": "https://www.hopefridge.com/",
          "description": "Providing mutual aid via free food and household products directly to communities in the Fox Valley of Northeast Wisconsin.",
          "links": [
            {
              "type": "instagram",
              "url": "https://www.instagram.com/hopefridgefv/"
            }
          ]
        },
        {
          "name": "Diverse and Resilient Appleton",
          "url": "https://www.instagram.com/diverseandresilientappleton/",
          "description": "We see a future in which LGBTQ people in Wisconsin thrive, living healthy, satisfying lives in safe, supportive communities."
        },
        {
          "name": "ESTHER Fox Valley",
          "url": "https://esther-foxvalley.org/",
          "description": "ESTHER is an interfaith social-justice organization. We are grassroots and non-profit, focusing our work in the Fox Valley region of Wisconsin."
        }
      ]
    }
  ]
}