{
  "slug": "new-paltz",
  "title": "New Paltz",
  "state": "new-york",
  "parent": "new-york",
  "sections": [
    {
      "id": "section-0",
      "title": "",
      "initiatives": [
        {
          "name": "Millions of Butterflies",
          "url": "https://www.millionsofbutterflies.org/",
          "description": "A grassroots mutual aid collective fostering community support and solidarity in New Paltz. They coordinate direct assistance, resource sharing, and community care initiatives while building power through collective action and creating spaces for community resilience."
        },
        {
          "name": "New Paltz Free Food Fridge",
          "url": "https://www.instagram.com/newpaltzfreefoodfridge/",
          "description": "A community mutual aid initiative providing free food access at the Village Hall (25 Plattekill Ave). The fridge offers a space for neighbors to share food resources, operating on the principle that food is a human right and should be freely accessible to all community members."
        }
      ]
    }
  ]
}